{
    "languages": [
        {
            "id": "1",
            "name": "HTML",
            "slug": "html",
            "description": "Esercitati su HTML",
            "color": "#E34C26"
        },
        {
            "id": "2",
            "name": "CSS",
            "slug": "css",
            "description": "Esercitati su CSS",
            "color": "#264DE4"
        },
        {
            "id": "3",
            "name": "JavaScript",
            "slug": "javascript",
            "description": "Esercitati su JavaScript",
            "color": "#F0DB4F"
        },
        {
            "id": "4",
            "name": "Vue.js",
            "slug": "vue",
            "description": "Esercitati su Vue.js",
            "color": "#42b883"
        }
    ]
}